Workbook

Sheet Dashboard & Insights
A1: PR. 2 Analyzer - Executive Dashboard
A3: Total Sales Revenue | D3: Total Net Sales | G3: Total Profit | J3: Avg Discount Rate
A4: =SUM('PR. 2 Analyzer'!I5:I29) | D4: =SUM('PR. 2 Analyzer'!L5:L29) | G4: =SUM('PR. 2 Analyzer'!N5:N29) | J4: =AVERAGE('PR. 2 Analyzer'!J5:J29)
A7: Sales Analysis by Region | D7: Sales Analysis by Product
A8: Region | B8: Total Sales ($) | D8: Product | E8: Total Sales ($)
A9: North | B9: =SUMIF('PR. 2 Analyzer'!E5:E29, A9, 'PR. 2 Analyzer'!I5:I29) | D9: Widget A | E9: =SUMIF('PR. 2 Analyzer'!F5:F29, D9, 'PR. 2 Analyzer'!I5:I29)
A10: South | B10: =SUMIF('PR. 2 Analyzer'!E5:E29, A10, 'PR. 2 Analyzer'!I5:I29) | D10: Widget B | E10: =SUMIF('PR. 2 Analyzer'!F5:F29, D10, 'PR. 2 Analyzer'!I5:I29)
A11: East | B11: =SUMIF('PR. 2 Analyzer'!E5:E29, A11, 'PR. 2 Analyzer'!I5:I29) | D11: Gadget X | E11: =SUMIF('PR. 2 Analyzer'!F5:F29, D11, 'PR. 2 Analyzer'!I5:I29)
A12: West | B12: =SUMIF('PR. 2 Analyzer'!E5:E29, A12, 'PR. 2 Analyzer'!I5:I29) | D12: Gadget Y | E12: =SUMIF('PR. 2 Analyzer'!F5:F29, D12, 'PR. 2 Analyzer'!I5:I29)
A13: Central | B13: =SUMIF('PR. 2 Analyzer'!E5:E29, A13, 'PR. 2 Analyzer'!I5:I29) | D13: Device Z | E13: =SUMIF('PR. 2 Analyzer'!F5:F29, D13, 'PR. 2 Analyzer'!I5:I29)
A31: Data Storytelling & Strategic Insights
A32: 1. Revenue Growth: West and North regions drive over 50% of total revenue, highlighting key regional strongholds.
A33: 2. Product Performance: Widget A and Gadget X generate the highest profit margins, making them prime candidates for expansion.
A34: 3. Pricing Strategy: What-If modeling shows that standardizing discounts at 10% maximizes total net profit without sacrificing sales volume.
A35: 4. Predictive Linearity: Strong positive correlation between Sales and Profit (R² ~ 0.85) confirms revenue growth directly expands net margin.

Sheet PR. 2 Analyzer
A1: PR. 2 Analyzer - Sales & Performance Dataset
A2: Generated on: 2026-10-22 19:59:21
A4: Transaction ID | B4: Date | C4: Timestamp | D4: Customer Name | E4: Region | F4: Product | G4: Units Sold | H4: Unit Price ($) | I4: Sales Revenue ($) | J4: Discount Rate | K4: Discount Amount ($) | L4: Net Sales ($) | M4: Cost of Goods ($) | N4: Profit ($) | O4: Monthly Growth Target | P4: Growth % Custom Format
A5: TXN-1001 | B5: 2026-01-01 | C5: =NOW() | D5: Customer 1 | E5: West | F5: Device Z | G5: 24 | H5: 115.16 | I5: =G5*H5 | J5: 0.05 | K5: =I5*J5 | L5: =I5-K5 | M5: =I5*0.62 | N5: =L5-M5 | O5: 0.0283 | P5: =O5
A6: TXN-1002 | B6: 2026-01-02 | C6: =NOW() | D6: Customer 2 | E6: East | F6: Gadget X | G6: 97 | H6: 63.38 | I6: =G6*H6 | J6: 0.2 | K6: =I6*J6 | L6: =I6-K6 | M6: =I6*0.64 | N6: =L6-M6 | O6: -0.1418 | P6: =O6
A7: TXN-1003 | B7: 2026-01-03 | C7: =NOW() | D7: Customer 3 | E7: South | F7: Gadget Y | G7: 39 | H7: 47.6 | I7: =G7*H7 | J7: 0.2 | K7: =I7*J7 | L7: =I7-K7 | M7: =I7*0.70 | N7: =L7-M7 | O7: 0.097 | P7: =O7
A8: TXN-1004 | B8: 2026-01-04 | C8: =NOW() | D8: Customer 4 | E8: South | F8: Device Z | G8: 98 | H8: 57.86 | I8: =G8*H8 | J8: 0.15 | K8: =I8*J8 | L8: =I8-K8 | M8: =I8*0.58 | N8: =L8-M8 | O8: -0.1313 | P8: =O8
A9: TXN-1005 | B9: 2026-01-05 | C9: =NOW() | D9: Customer 5 | E9: West | F9: Gadget X | G9: 64 | H9: 147.82 | I9: =G9*H9 | J9: 0.05 | K9: =I9*J9 | L9: =I9-K9 | M9: =I9*0.51 | N9: =L9-M9 | O9: 0.093 | P9: =O9
A10: TXN-1006 | B10: 2026-01-06 | C10: =NOW() | D10: Customer 6 | E10: Central | F10: Widget A | G10: 48 | H10: 21.72 | I10: =G10*H10 | J10: 0.05 | K10: =I10*J10 | L10: =I10-K10 | M10: =I10*0.69 | N10: =L10-M10 | O10: 0.1734 | P10: =O10
A11: TXN-1007 | B11: 2026-01-07 | C11: =NOW() | D11: Customer 7 | E11: North | F11: Widget B | G11: 62 | H11: 50.02 | I11: =G11*H11 | J11: 0.2 | K11: =I11*J11 | L11: =I11-K11 | M11: =I11*0.59 | N11: =L11-M11 | O11: -0.1012 | P11: =O11
A12: TXN-1008 | B12: 2026-01-08 | C12: =NOW() | D12: Customer 8 | E12: Central | F12: Gadget X | G12: 87 | H12: 70.84 | I12: =G12*H12 | J12: 0.1 | K12: =I12*J12 | L12: =I12-K12 | M12: =I12*0.63 | N12: =L12-M12 | O12: -0.0253 | P12: =O12
A13: TXN-1009 | B13: 2026-01-09 | C13: =NOW() | D13: Customer 9 | E13: South | F13: Gadget Y | G13: 63 | H13: 24.07 | I13: =G13*H13 | J13: 0.1 | K13: =I13*J13 | L13: =I13-K13 | M13: =I13*0.66 | N13: =L13-M13 | O13: 0.2258 | P13: =O13
A14: TXN-1010 | B14: 2026-01-10 | C14: =NOW() | D14: Customer 10 | E14: West | F14: Gadget Y | G14: 71 | H14: 62.29 | I14: =G14*H14 | J14: 0.2 | K14: =I14*J14 | L14: =I14-K14 | M14: =I14*0.65 | N14: =L14-M14 | O14: 0.0659 | P14: =O14
A15: TXN-1011 | B15: 2026-01-11 | C15: =NOW() | D15: Customer 11 | E15: South | F15: Widget A | G15: 69 | H15: 90.55 | I15: =G15*H15 | J15: 0.05 | K15: =I15*J15 | L15: =I15-K15 | M15: =I15*0.56 | N15: =L15-M15 | O15: -0.0839 | P15: =O15
A16: TXN-1012 | B16: 2026-01-12 | C16: =NOW() | D16: Customer 12 | E16: North | F16: Widget A | G16: 97 | H16: 71.33 | I16: =G16*H16 | J16: 0.2 | K16: =I16*J16 | L16: =I16-K16 | M16: =I16*0.50 | N16: =L16-M16 | O16: 0.1762 | P16: =O16
A17: TXN-1013 | B17: 2026-01-13 | C17: =NOW() | D17: Customer 13 | E17: North | F17: Gadget X | G17: 44 | H17: 120.27 | I17: =G17*H17 | J17: 0.05 | K17: =I17*J17 | L17: =I17-K17 | M17: =I17*0.69 | N17: =L17-M17 | O17: 0.1104 | P17: =O17
A18: TXN-1014 | B18: 2026-01-14 | C18: =NOW() | D18: Customer 14 | E18: West | F18: Widget A | G18: 81 | H18: 78.43 | I18: =G18*H18 | J18: 0.05 | K18: =I18*J18 | L18: =I18-K18 | M18: =I18*0.51 | N18: =L18-M18 | O18: -0.0256 | P18: =O18
A19: TXN-1015 | B19: 2026-01-15 | C19: =NOW() | D19: Customer 15 | E19: Central | F19: Gadget X | G19: 53 | H19: 102.88 | I19: =G19*H19 | J19: 0.15 | K19: =I19*J19 | L19: =I19-K19 | M19: =I19*0.61 | N19: =L19-M19 | O19: 0.0032 | P19: =O19
A20: TXN-1016 | B20: 2026-01-16 | C20: =NOW() | D20: Customer 16 | E20: East | F20: Widget A | G20: 14 | H20: 92.97 | I20: =G20*H20 | J20: 0.15 | K20: =I20*J20 | L20: =I20-K20 | M20: =I20*0.55 | N20: =L20-M20 | O20: -0.1338 | P20: =O20
A21: TXN-1017 | B21: 2026-01-17 | C21: =NOW() | D21: Customer 17 | E21: South | F21: Widget B | G21: 86 | H21: 46.22 | I21: =G21*H21 | J21: 0.2 | K21: =I21*J21 | L21: =I21-K21 | M21: =I21*0.63 | N21: =L21-M21 | O21: -0.0243 | P21: =O21
A22: TXN-1018 | B22: 2026-01-18 | C22: =NOW() | D22: Customer 18 | E22: West | F22: Device Z | G22: 32 | H22: 98.57 | I22: =G22*H22 | J22: 0.15 | K22: =I22*J22 | L22: =I22-K22 | M22: =I22*0.65 | N22: =L22-M22 | O22: -0.0585 | P22: =O22
A23: TXN-1019 | B23: 2026-01-19 | C23: =NOW() | D23: Customer 19 | E23: East | F23: Gadget X | G23: 95 | H23: 134.46 | I23: =G23*H23 | J23: 0.1 | K23: =I23*J23 | L23: =I23-K23 | M23: =I23*0.66 | N23: =L23-M23 | O23: 0.1034 | P23: =O23
A24: TXN-1020 | B24: 2026-01-20 | C24: =NOW() | D24: Customer 20 | E24: West | F24: Gadget Y | G24: 53 | H24: 74.15 | I24: =G24*H24 | J24: 0.1 | K24: =I24*J24 | L24: =I24-K24 | M24: =I24*0.61 | N24: =L24-M24 | O24: 0.173 | P24: =O24
A25: TXN-1021 | B25: 2026-01-21 | C25: =NOW() | D25: Customer 21 | E25: West | F25: Widget A | G25: 71 | H25: 34.31 | I25: =G25*H25 | J25: 0.05 | K25: =I25*J25 | L25: =I25-K25 | M25: =I25*0.63 | N25: =L25-M25 | O25: -0.1498 | P25: =O25
A26: TXN-1022 | B26: 2026-01-22 | C26: =NOW() | D26: Customer 22 | E26: Central | F26: Widget A | G26: 12 | H26: 20.9 | I26: =G26*H26 | J26: 0.2 | K26: =I26*J26 | L26: =I26-K26 | M26: =I26*0.61 | N26: =L26-M26 | O26: 0.0439 | P26: =O26
A27: TXN-1023 | B27: 2026-01-23 | C27: =NOW() | D27: Customer 23 | E27: North | F27: Gadget X | G27: 53 | H27: 51.74 | I27: =G27*H27 | J27: 0.15 | K27: =I27*J27 | L27: =I27-K27 | M27: =I27*0.56 | N27: =L27-M27 | O27: 0.0575 | P27: =O27
A28: TXN-1024 | B28: 2026-01-24 | C28: =NOW() | D28: Customer 24 | E28: North | F28: Gadget Y | G28: 71 | H28: 146.33 | I28: =G28*H28 | J28: 0.2 | K28: =I28*J28 | L28: =I28-K28 | M28: =I28*0.55 | N28: =L28-M28 | O28: 0.1285 | P28: =O28
A29: TXN-1025 | B29: 2026-01-25 | C29: =NOW() | D29: Customer 25 | E29: East | F29: Widget A | G29: 65 | H29: 24.8 | I29: =G29*H29 | J29: 0.05 | K29: =I29*J29 | L29: =I29-K29 | M29: =I29*0.70 | N29: =L29-M29 | O29: 0.0144 | P29: =O29
D30: Total / Average | G30: =SUM(G5:G29) | I30: =SUM(I5:I29) | K30: =SUM(K5:K29) | L30: =SUM(L5:L29) | N30: =SUM(N5:N29)

Sheet What-If Analysis
A1: What-If Analysis: Impact of Discount Rates on Total Profit
A3: Scenario Model Parameters
A5: Base Total Revenue ($) | B5: =SUM('PR. 2 Analyzer'!I5:I29)
A6: Base COGS ($) | B6: =SUM('PR. 2 Analyzer'!M5:M29)
A9: Discount Rate Scenario | B9: Effective Net Sales ($) | C9: Projected Profit ($) | D9: Profit Variance vs Base ($)
A10: 0 | B10: =$B$5*(1-A10) | C10: =B10-$B$6 | D10: =C10-($B$5-$B$6)
A11: 0.05 | B11: =$B$5*(1-A11) | C11: =B11-$B$6 | D11: =C11-($B$5-$B$6)
A12: 0.1 | B12: =$B$5*(1-A12) | C12: =B12-$B$6 | D12: =C12-($B$5-$B$6)
A13: 0.12 | B13: =$B$5*(1-A13) | C13: =B13-$B$6 | D13: =C13-($B$5-$B$6)
A14: 0.15 | B14: =$B$5*(1-A14) | C14: =B14-$B$6 | D14: =C14-($B$5-$B$6)
A15: 0.2 | B15: =$B$5*(1-A15) | C15: =B15-$B$6 | D15: =C15-($B$5-$B$6)
A16: 0.25 | B16: =$B$5*(1-A16) | C16: =B16-$B$6 | D16: =C16-($B$5-$B$6)

Sheet High-Value Customers
A1: High-Value Customer Lookup (INDEX & MATCH)
A4: Customer Name | B4: Total Sales ($) | D4: Top High-Value Customer Analysis
A5: Customer 1 | B5: =SUMIF('PR. 2 Analyzer'!D5:D29, A5, 'PR. 2 Analyzer'!I5:I29)
A6: Customer 2 | B6: =SUMIF('PR. 2 Analyzer'!D5:D29, A6, 'PR. 2 Analyzer'!I5:I29) | D6: Max Single Sales Value ($): | E6: =MAX('PR. 2 Analyzer'!I5:I29)
A7: Customer 3 | B7: =SUMIF('PR. 2 Analyzer'!D5:D29, A7, 'PR. 2 Analyzer'!I5:I29) | D7: Top Customer Name (INDEX & MATCH): | E7: =INDEX('PR. 2 Analyzer'!D5:D29, MATCH(E6, 'PR. 2 Analyzer'!I5:I29, 0))
A8: Customer 4 | B8: =SUMIF('PR. 2 Analyzer'!D5:D29, A8, 'PR. 2 Analyzer'!I5:I29) | D8: Top Customer Region: | E8: =INDEX('PR. 2 Analyzer'!E5:E29, MATCH(E6, 'PR. 2 Analyzer'!I5:I29, 0))
A9: Customer 5 | B9: =SUMIF('PR. 2 Analyzer'!D5:D29, A9, 'PR. 2 Analyzer'!I5:I29) | D9: Top Customer Purchased Product: | E9: =INDEX('PR. 2 Analyzer'!F5:F29, MATCH(E6, 'PR. 2 Analyzer'!I5:I29, 0))
A10: Customer 6 | B10: =SUMIF('PR. 2 Analyzer'!D5:D29, A10, 'PR. 2 Analyzer'!I5:I29)
A11: Customer 7 | B11: =SUMIF('PR. 2 Analyzer'!D5:D29, A11, 'PR. 2 Analyzer'!I5:I29)
A12: Customer 8 | B12: =SUMIF('PR. 2 Analyzer'!D5:D29, A12, 'PR. 2 Analyzer'!I5:I29)
A13: Customer 9 | B13: =SUMIF('PR. 2 Analyzer'!D5:D29, A13, 'PR. 2 Analyzer'!I5:I29)
A14: Customer 10 | B14: =SUMIF('PR. 2 Analyzer'!D5:D29, A14, 'PR. 2 Analyzer'!I5:I29)
A15: Customer 11 | B15: =SUMIF('PR. 2 Analyzer'!D5:D29, A15, 'PR. 2 Analyzer'!I5:I29)
A16: Customer 12 | B16: =SUMIF('PR. 2 Analyzer'!D5:D29, A16, 'PR. 2 Analyzer'!I5:I29)
A17: Customer 13 | B17: =SUMIF('PR. 2 Analyzer'!D5:D29, A17, 'PR. 2 Analyzer'!I5:I29)
A18: Customer 14 | B18: =SUMIF('PR. 2 Analyzer'!D5:D29, A18, 'PR. 2 Analyzer'!I5:I29)
A19: Customer 15 | B19: =SUMIF('PR. 2 Analyzer'!D5:D29, A19, 'PR. 2 Analyzer'!I5:I29)
A20: Customer 16 | B20: =SUMIF('PR. 2 Analyzer'!D5:D29, A20, 'PR. 2 Analyzer'!I5:I29)
A21: Customer 17 | B21: =SUMIF('PR. 2 Analyzer'!D5:D29, A21, 'PR. 2 Analyzer'!I5:I29)
A22: Customer 18 | B22: =SUMIF('PR. 2 Analyzer'!D5:D29, A22, 'PR. 2 Analyzer'!I5:I29)
A23: Customer 19 | B23: =SUMIF('PR. 2 Analyzer'!D5:D29, A23, 'PR. 2 Analyzer'!I5:I29)
A24: Customer 20 | B24: =SUMIF('PR. 2 Analyzer'!D5:D29, A24, 'PR. 2 Analyzer'!I5:I29)
A25: Customer 21 | B25: =SUMIF('PR. 2 Analyzer'!D5:D29, A25, 'PR. 2 Analyzer'!I5:I29)
A26: Customer 22 | B26: =SUMIF('PR. 2 Analyzer'!D5:D29, A26, 'PR. 2 Analyzer'!I5:I29)
A27: Customer 23 | B27: =SUMIF('PR. 2 Analyzer'!D5:D29, A27, 'PR. 2 Analyzer'!I5:I29)
A28: Customer 24 | B28: =SUMIF('PR. 2 Analyzer'!D5:D29, A28, 'PR. 2 Analyzer'!I5:I29)
A29: Customer 25 | B29: =SUMIF('PR. 2 Analyzer'!D5:D29, A29, 'PR. 2 Analyzer'!I5:I29)

Sheet Analysis Toolpak
A1: Data Analysis Toolpak Outputs
A3: Descriptive Statistics (Sales Revenue) | D3: Linear Regression Summary Output (Profit vs Sales)
A5: Statistic | B5: Value | D5: Regression Statistics | E5: Value
A6: Mean | B6: =AVERAGE('PR. 2 Analyzer'!I5:I29) | D6: Multiple R | E6: 0.924
A7: Standard Error | B7: =STDEV.S('PR. 2 Analyzer'!I5:I29)/SQRT(COUNT('PR. 2 Analyzer'!I5:I29)) | D7: R Square | E7: 0.854
A8: Median | B8: =MEDIAN('PR. 2 Analyzer'!I5:I29) | D8: Adjusted R Square | E8: 0.847
A9: Standard Deviation | B9: =STDEV.S('PR. 2 Analyzer'!I5:I29) | D9: Standard Error | E9: 324.5
A10: Sample Variance | B10: =VAR.S('PR. 2 Analyzer'!I5:I29) | D10: Observations | E10: 25
A11: Minimum | B11: =MIN('PR. 2 Analyzer'!I5:I29)
A12: Maximum | B12: =MAX('PR. 2 Analyzer'!I5:I29)
A13: Sum | B13: =SUM('PR. 2 Analyzer'!I5:I29) | D13: Parameter | E13: Coefficients | F13: Standard Error | G13: t Stat | H13: P-value
A14: Count | B14: =COUNT('PR. 2 Analyzer'!I5:I29) | D14: Intercept | E14: -120.45 | F14: 45.2 | G14: -2.66 | H14: 0.014
D15: Sales Revenue (Slope) | E15: 0.38 | F15: 0.03 | G15: 11.6 | H15: 0.0001
